lasp_opensearch_data_center/__init__.py
lasp_opensearch_data_center/constructs/__init__.py
lasp_opensearch_data_center/constructs/backend_storage.py
lasp_opensearch_data_center/constructs/certificate.py
lasp_opensearch_data_center/constructs/constants.py
lasp_opensearch_data_center/constructs/frontend.py
lasp_opensearch_data_center/constructs/frontend_storage.py
lasp_opensearch_data_center/constructs/ingest_orchestration.py
lasp_opensearch_data_center/constructs/networking.py
lasp_opensearch_data_center/constructs/opensearch.py
lasp_opensearch_data_center/ingest_status.py
lasp_opensearch_data_center/lambda/Dockerfile
lasp_opensearch_data_center/lambda/lambda_entrypoint.sh
lasp_opensearch_data_center/lambda/opensearch_data_center_lambda_runtime/__init__.py
lasp_opensearch_data_center/lambda/opensearch_data_center_lambda_runtime/snapshot_handler.py
lasp_opensearch_data_center/lambda/pyproject.toml
lasp_opensearch_data_center-1.0.7.dist-info/LICENSE.txt
lasp_opensearch_data_center-1.0.7.dist-info/METADATA
lasp_opensearch_data_center-1.0.7.dist-info/WHEEL
lasp_opensearch_data_center-1.0.7.dist-info/RECORD
